{
  "updated_at": 1765059103,
  "products": [
    {
      "source": "ebay",
      "provider": "ebay",
      "keyword": "air fryer",
      "title": "bella PRO - 6-qt. Touchscreen Air Fryer - Stainless Steel",
      "price": 39.99,
      "currency": "USD",
      "image_url": "https://i.ebayimg.com/images/g/CjIAAeSwob9pNKfG/s-l225.jpg",
      "url": "https://www.ebay.com/itm/196833932009?_skw=air+fryer&hash=item2dd43772e9%3Ag%3ACjIAAeSwob9pNKfG&mkcid=1&mkrid=711-53200-19255-0&mkevt=1&campid=5339121799&customid=air_fryer&toolid=10001",
      "seller_feedback": 901364,
      "top_rated": false,
      "seller_username": "best_buy",
      "inserted_at": "2024-11-21T02:09:27.000Z",
      "signals": 9.0,
      "tags": [
        "air fryer"
      ],
      "caption": "bella PRO - 6-qt. Touchscreen Air Fryer - Stainless Steel \u2022 USD 39.99",
      "headline": "\ud83d\udd25\u2728 bella PRO - 6-qt. Touchscreen Air Fryer - Stainless Steel",
      "blurb": "USD 39.99 steal. Limited stock\u2014grab it now!",
      "emojis": "\ud83d\udd25\u2728"
    },
    {
      "source": "ebay",
      "provider": "ebay",
      "keyword": "air fryer",
      "title": "Ninja - Foodi 6-in-1 10-qt. XL 2-Basket Air Fryer with DualZone Technology & ...",
      "price": 129.99,
      "currency": "USD",
      "image_url": "https://i.ebayimg.com/images/g/FdIAAeSwE3hpMMUY/s-l225.jpg",
      "url": "https://www.ebay.com/itm/205800943363?_skw=air+fryer&hash=item2feab12f03%3Ag%3AFdIAAeSwE3hpMMUY&mkcid=1&mkrid=711-53200-19255-0&mkevt=1&campid=5339121799&customid=air_fryer&toolid=10001",
      "seller_feedback": 901364,
      "top_rated": false,
      "seller_username": "best_buy",
      "inserted_at": "2025-10-22T15:52:43.000Z",
      "signals": 9.0,
      "tags": [
        "air fryer"
      ],
      "caption": "Ninja - Foodi 6-in-1 10-qt. XL 2-Basket Air Fryer with DualZone Technology & ... \u2022 USD 129.99",
      "headline": "\ud83d\udd25\u2728 Ninja - Foodi 6-in-1 10-qt. XL 2-Basket Air Fryer with DualZone Technology & ...",
      "blurb": "USD 129.99 steal. Limited stock\u2014grab it now!",
      "emojis": "\ud83d\udd25\u2728"
    },
    {
      "source": "ebay",
      "provider": "ebay",
      "keyword": "mechanical keyboard deals",
      "title": "Logitech MK470 Slim Wireless Keyboard and Mouse Combo - Black/Gray",
      "price": 24.95,
      "currency": "USD",
      "image_url": "https://i.ebayimg.com/images/g/kYAAAeSwEE5pM6as/s-l225.jpg",
      "url": "https://www.ebay.com/itm/315781118209?_skw=mechanical+keyboard+deals&hash=item4986057901%3Ag%3AkYAAAeSwEE5pM6as&amdata=enc%3AAQAKAAAA8PeG5RIuIyokJHJy903%2F5UbfyV2HfsZQuYuoIWfGa6uKwbCJuGpp7%2FYhQIDNNoKg3WAPzRbYw8ZPR62oPjFrhte8t02MmWNMj%2FJPALZPgK1bZWgLVzxdsd4LLs96o1ChHOTxvBpNEw3k2lEvJmu5BGZz6ZwM8zkWWnhxCXBKZQd7cxZY6oG3U%2B7RBYn%2Bbt%2FL3h7qS6tCRpzvTBqySEKO9FGrRWFN%2Bmp23F%2BzFp5ahCQ%2BVV3ktlJTA6hJO0ym2HevuSbyWuJGowbLt3DD9OX6cvvSWG1ft3c7L2hwwkge%2FUZmu0X8eGpAFNM3jkd9qeixCw%3D%3D&mkcid=1&mkrid=711-53200-19255-0&mkevt=1&campid=5339121799&customid=mechanical_keyboard&toolid=10001",
      "seller_feedback": 860353,
      "top_rated": false,
      "seller_username": "a4c",
      "inserted_at": "2024-09-23T23:43:37.000Z",
      "signals": 9.0,
      "tags": [
        "mechanical keyboard"
      ],
      "caption": "Logitech MK470 Slim Wireless Keyboard and Mouse Combo - Black/Gray \u2022 USD 24.95",
      "headline": "\ud83d\udd79\ufe0f Logitech MK470 Slim Wireless Keyboard and Mouse Combo - Black/Gray",
      "blurb": "USD 24.95 steal. Limited stock\u2014grab it now!",
      "emojis": "\ud83d\udd79\ufe0f\ud83c\udfae\u2728"
    },
    {
      "source": "ebay",
      "provider": "ebay",
      "keyword": "cordless vacuum",
      "title": "BISSELL Featherweight Lightweight Stick Vacuum - 2033M",
      "price": 19.99,
      "currency": "USD",
      "image_url": "https://i.ebayimg.com/images/g/1Q0AAeSwUTlpNJaF/s-l225.jpg",
      "url": "https://www.ebay.com/itm/205901826590?_skw=cordless+vacuum&hash=item2ff0b48a1e%3Ag%3A1Q0AAeSwUTlpNJaF&mkcid=1&mkrid=711-53200-19255-0&mkevt=1&campid=5339121799&customid=cordless_vacuum&toolid=10001",
      "seller_feedback": 785207,
      "top_rated": false,
      "seller_username": "bullseye_deals",
      "inserted_at": "2025-12-06T15:20:47.000Z",
      "signals": 9.0,
      "tags": [
        "cordless vacuum"
      ],
      "caption": "BISSELL Featherweight Lightweight Stick Vacuum - 2033M \u2022 USD 19.99",
      "headline": "\ud83c\udfe0\ud83d\udecb BISSELL Featherweight Lightweight Stick Vacuum - 2033M",
      "blurb": "USD 19.99 steal. Limited stock\u2014grab it now!",
      "emojis": "\ud83c\udfe0\ud83d\udecb\ufe0f\u2728"
    },
    {
      "source": "ebay",
      "provider": "ebay",
      "keyword": "air fryer",
      "title": "Gourmia 8QT Air Fryer - 12 One-Touch Functions, Guided Cooking",
      "price": 50.99,
      "currency": "USD",
      "image_url": "https://i.ebayimg.com/images/g/BIIAAeSwYOFpM~XT/s-l225.jpg",
      "url": "https://www.ebay.com/itm/205830074901?_skw=air+fryer&hash=item2fec6db215%3Ag%3ABIIAAeSwYOFpM~XT&mkcid=1&mkrid=711-53200-19255-0&mkevt=1&campid=5339121799&customid=air_fryer&toolid=10001",
      "seller_feedback": 785207,
      "top_rated": false,
      "seller_username": "bullseye_deals",
      "inserted_at": "2025-11-06T13:43:46.000Z",
      "signals": 9.0,
      "tags": [
        "air fryer"
      ],
      "caption": "Gourmia 8QT Air Fryer - 12 One-Touch Functions, Guided Cooking \u2022 USD 50.99",
      "headline": "\ud83c\udfe0\ud83d\udecb Gourmia 8QT Air Fryer - 12 One-Touch Functions, Guided Cooking",
      "blurb": "USD 50.99 steal. Limited stock\u2014grab it now!",
      "emojis": "\ud83c\udfe0\ud83d\udecb\ufe0f\u2728"
    },
    {
      "source": "ebay",
      "provider": "ebay",
      "keyword": "cordless vacuum deals",
      "title": "Shark UZ565H Pro Cordless Vacuum Clean Sense IQ & MultiFLEX Technology (Refurbis",
      "price": 129.95,
      "currency": "USD",
      "image_url": "https://i.ebayimg.com/images/g/OAYAAeSw30VpNJfo/s-l225.jpg",
      "url": "https://www.ebay.com/itm/317199022760?_skw=cordless+vacuum+deals&hash=item49da88faa8%3Ag%3AOAYAAeSw30VpNJfo&mkcid=1&mkrid=711-53200-19255-0&mkevt=1&campid=5339121799&customid=cordless_vacuum&toolid=10001",
      "seller_feedback": 653553,
      "top_rated": false,
      "seller_username": "buydig",
      "inserted_at": "2025-08-21T17:00:21.000Z",
      "signals": 9.0,
      "tags": [
        "cordless vacuum"
      ],
      "caption": "Shark UZ565H Pro Cordless Vacuum Clean Sense IQ & MultiFLEX Technology (Refurbis \u2022 USD 129.95",
      "headline": "\ud83c\udfe0\ud83d\udecb Shark UZ565H Pro Cordless Vacuum Clean Sense IQ & MultiFLEX Technology (Refurbis",
      "blurb": "USD 129.95 steal. Limited stock\u2014grab it now!",
      "emojis": "\ud83c\udfe0\ud83d\udecb\ufe0f\u2728"
    }
  ]
}